mocap_aws_io/__init__.py
mocap_aws_io/axengine_1755691756_313968992.py
mocap_aws_io/notifiers/__init__.py
mocap_aws_io/notifiers/sns_notifier.py
mocap_aws_io/notifiers/webapp_notifier.py
mocap_aws_io/operations/__init__.py
mocap_aws_io/operations/opsDownloadDataset.py
mocap_aws_io/operations/opsDownloadInputs.py
mocap_aws_io/operations/opsFinalizeARun.py
mocap_aws_io/operations/opsOnFailure.py
mocap_aws_io/operations/opsPrepareActorProfile.py
mocap_aws_io/operations/opsPrepareRunData.py
mocap_aws_io/operations/opsUploadOutputs.py
mocap_aws_io/operations/opsWebappOutputs.py
mocap_aws_io/operations/opsZipData.py
mocap_aws_io/scripts/__init__.py
mocap_aws_io/scripts/start_aws_pipeline.py
mocap_aws_io/utils/__init__.py
mocap_aws_io/utils/boto3_utils.py
mocap_aws_io/utils/download_settings.py
mocap_aws_io/utils/ec2_metadata.py
mocap_aws_io/utils/file_utils.py
mocap_aws_io/utils/logger.py
mocap_aws_io/utils/logging_settings.yaml
mocap_aws_io/utils/presentation_sync.py
mocap_aws_io/utils/rclone.py
mocap_aws_io/utils/rclone_util.py
mocap_aws_io-2.12.2.dist-info/METADATA
mocap_aws_io-2.12.2.dist-info/WHEEL
mocap_aws_io-2.12.2.dist-info/entry_points.txt
mocap_aws_io-2.12.2.dist-info/RECORD
